ShanHeUniversity/__init__.py
ShanHeUniversity/MobAI/__init__.py
ShanHeUniversity/MobAI/webapi/__init__.py
ShanHeUniversity/MobAI/webapi/v1/ApiData.py
ShanHeUniversity/MobAI/webapi/v1/__init__.py
ShanHeUniversity/MobAI/webapi/v1/api.py
ShanHeUniversity/MobAI/webapi/v1/common.py
ShanHeUniversity/MobAI/webapi/v1/error.py
ShanHeUniversity/MobAI/webapi/v2/ApiData.py
ShanHeUniversity/MobAI/webapi/v2/__init__.py
ShanHeUniversity/MobAI/webapi/v2/api.py
ShanHeUniversity/MobAI/webapi/v2/common.py
ShanHeUniversity/MobAI/webapi/v2/error.py
ShanHeUniversity-0.2.1.dist-info/METADATA
ShanHeUniversity-0.2.1.dist-info/WHEEL
ShanHeUniversity-0.2.1.dist-info/top_level.txt
ShanHeUniversity-0.2.1.dist-info/RECORD
