Metadata-Version: 2.1
Name: ShanHeUniversity
Version: 0.2.1
Summary: This is a module for MobAI.API.
Home-page: https://github.com/ShanHeUniversityOfficial/pypi-ShanHeUniversity
Author: MoYeRanQianZhi
Author-email: moyeranqianzhi@gmail.com
License: MIT License
Classifier: Development Status :: 3 - Alpha
Classifier: Intended Audience :: Developers
Classifier: License :: OSI Approved :: MIT License
Classifier: Programming Language :: Python
Classifier: Programming Language :: Python :: 3
Classifier: Programming Language :: Python :: 3.6
Classifier: Programming Language :: Python :: 3.7
Classifier: Programming Language :: Python :: 3.8
Classifier: Programming Language :: Python :: 3.9
Classifier: Programming Language :: Python :: 3.10
Classifier: Programming Language :: Python :: 3.11
Classifier: Programming Language :: Python :: 3.12
Requires: requests
Requires-Python: >=3.6.0
